libadalina_core/__init__.py
libadalina_core/__main__.py
libadalina_core/exceptions/__init__.py
libadalina_core/exceptions/input_file_exception.py
libadalina_core/graph_extraction/__init__.py
libadalina_core/graph_extraction/builders/__init__.py
libadalina_core/graph_extraction/builders/graph_builder.py
libadalina_core/graph_extraction/readers/__init__.py
libadalina_core/graph_extraction/readers/open_street_map.py
libadalina_core/graph_extraction/readers/reader.py
libadalina_core/graph_extraction/utils/__init__.py
libadalina_core/graph_extraction/utils/search_address.py
libadalina_core/graph_extraction/writers/__init__.py
libadalina_core/graph_extraction/writers/to_csv.py
libadalina_core/graph_extraction/writers/to_geopackage.py
libadalina_core/graph_extraction/writers/to_shapefile.py
libadalina_core/readers/__init__.py
libadalina_core/readers/csv.py
libadalina_core/readers/geopackage.py
libadalina_core/readers/read_dataset.py
libadalina_core/readers/shapefile.py
libadalina_core/sedona_configuration/__init__.py
libadalina_core/sedona_configuration/jdk_installer.py
libadalina_core/sedona_configuration/sedona_configuration.py
libadalina_core/sedona_utils/__init__.py
libadalina_core/sedona_utils/coordinate_formats.py
libadalina_core/sedona_utils/utils.py
libadalina_core/spatial_operators/__init__.py
libadalina_core/spatial_operators/multi_table_operators.py
libadalina_core/spatial_operators/single_table_operators.py
libadalina_core/writers/__init__.py
libadalina_core/writers/writers.py
libadalina_core-1.3.4.dist-info/licenses/LICENSE
libadalina_core-1.3.4.dist-info/METADATA
libadalina_core-1.3.4.dist-info/WHEEL
libadalina_core-1.3.4.dist-info/top_level.txt
libadalina_core-1.3.4.dist-info/RECORD
