Metadata-Version: 2.4
Name: libadalina-core
Version: 1.3.4
Summary: A library for spatial joins of geographic data
Author-email: Marco Casazza <d.marcocasazza@gmail.com>, Alberto Ceselli <alberto.ceselli@unimi.it>, Marco Premoli <marco.premoli@unimi.it>
License-Expression: MIT
Project-URL: Homepage, https://libadalinacore-6b2a95.gitlab.io/
Project-URL: Documentation, https://libadalinacore-6b2a95.gitlab.io/
Project-URL: Source, https://gitlab.com/amelia_unimi/libadalinacore
Classifier: Development Status :: 3 - Alpha
Classifier: Intended Audience :: Developers
Classifier: Programming Language :: Python :: 3
Classifier: Programming Language :: Python :: 3.10
Requires-Python: ~=3.10
License-File: LICENSE
Requires-Dist: apache-sedona[spark]==1.7.1
Requires-Dist: pyspark==3.3.2
Requires-Dist: pandas==2.2.3
Requires-Dist: geopandas==1.0.1
Requires-Dist: shapely==2.1.1
Requires-Dist: install-jdk==1.1.0
Requires-Dist: click==8.2.1
Requires-Dist: networkx==3.4.2
Provides-Extra: dev
Requires-Dist: pytest==8.4.1; extra == "dev"
Requires-Dist: black; extra == "dev"
Requires-Dist: isort; extra == "dev"
Requires-Dist: sphinx; extra == "dev"
Requires-Dist: pydata-sphinx-theme; extra == "dev"
Requires-Dist: nbsphinx; extra == "dev"
Requires-Dist: sphinx-collections; extra == "dev"
Dynamic: license-file
